nety/__init__.py
nety/__main__.py
nety/ccp_abc.py
nety/ccp_flask.py
nety/ccp_util.py
nety/models_asa.py
nety/models_cisco.py
nety/models_junos.py
nety/nety.py
nety/protocol_values.py
nety/version.py
Nety-1.3.0.dist-info/DESCRIPTION.rst
Nety-1.3.0.dist-info/METADATA
Nety-1.3.0.dist-info/metadata.json
Nety-1.3.0.dist-info/RECORD
Nety-1.3.0.dist-info/top_level.txt
Nety-1.3.0.dist-info/WHEEL
version_info/__init__.py
version_info/version.py
