Metadata-Version: 2.0
Name: Nety
Version: 1.3.0
Summary: Parse, Audit, Query, Build, and Modify Cisco IOS-style configurations
Home-page: https://github.com/YtenSoftware/Nety/
Author: Yten Software
Author-email: YtenSoftware@nocer.net
License: GPLv3
Keywords: Parse audit query modify Cisco IOS configuration
Platform: any
Classifier: Development Status :: 5 - Production/Stable
Classifier: Environment :: Plugins
Classifier: Intended Audience :: Developers
Classifier: Intended Audience :: System Administrators
Classifier: Intended Audience :: Information Technology
Classifier: Intended Audience :: Telecommunications Industry
Classifier: License :: OSI Approved :: GNU General Public License (GPL)
Classifier: Natural Language :: English
Classifier: Operating System :: OS Independent
Classifier: Programming Language :: Python
Classifier: Topic :: Communications
Classifier: Topic :: Internet
Classifier: Topic :: System :: Networking
Classifier: Topic :: System :: Networking :: Monitoring
Classifier: Topic :: Software Development :: Libraries :: Python Modules
Requires-Dist: ipaddress
Requires-Dist: dnspython3
Requires-Dist: colorama
